.coveragerc
.gitignore
LICENSE
MANIFEST.in
PKG-INFO
README.md
pytest.ini
setup.cfg
setup.py
img/screenshot-editor.png
tests/models.py
tests/requirements.txt
tests/settings.py
tests/test_blocks.py
tests/urls.py
tests/migrations/0001_initial.py
tests/migrations/__init__.py
wagtailcodeblocknocss/__init__.py
wagtailcodeblocknocss/blocks.py
wagtailcodeblocknocss/settings.py
wagtailcodeblocknocss/wagtail_hooks.py
wagtailcodeblocknocss.egg-info/PKG-INFO
wagtailcodeblocknocss.egg-info/SOURCES.txt
wagtailcodeblocknocss.egg-info/dependency_links.txt
wagtailcodeblocknocss.egg-info/not-zip-safe
wagtailcodeblocknocss.egg-info/requires.txt
wagtailcodeblocknocss.egg-info/top_level.txt
wagtailcodeblocknocss/static/wagtailcodeblocknocss/css/wagtail-code-block.css
wagtailcodeblocknocss/static/wagtailcodeblocknocss/css/wagtail-code-block.min.css
wagtailcodeblocknocss/static/wagtailcodeblocknocss/js/wagtailcodeblocknocss.js
wagtailcodeblocknocss/templates/wagtailcodeblocknocss/code_block.html
wagtailcodeblocknocss/templates/wagtailcodeblocknocss/code_block_form.html
wagtailcodeblocknocss/templates/wagtailcodeblocknocss/raw_code.html
wagtailcodeblocknocss/templatetags/__init__.py
wagtailcodeblocknocss/templatetags/wagtailcodeblock_tags.py